nbcmdio/__init__.py
nbcmdio/cli.py
nbcmdio/input.py
nbcmdio/output.py
nbcmdio/style.py
nbcmdio/utils.py
nbcmdio/widget.py
nbcmdio-1.8.78.dist-info/LICENSE
nbcmdio-1.8.78.dist-info/METADATA
nbcmdio-1.8.78.dist-info/WHEEL
nbcmdio-1.8.78.dist-info/entry_points.txt
nbcmdio-1.8.78.dist-info/top_level.txt
nbcmdio-1.8.78.dist-info/RECORD
