Metadata-Version: 2.1
Name: nbcmdio
Version: 1.8.78
Summary: 一个在终端中输出色彩斑斓、颜色多样内容以及快捷输入的强大工具。A powerful tool for outputting colorful content and enabling quick input in the terminal.
Home-page: https://github.com/YXPHOPE/NbCmdIO
Author: Cipen
Author-email: faithyxp@foxmail.com
Classifier: Programming Language :: Python :: 3
Classifier: License :: OSI Approved :: MIT License
Classifier: Operating System :: OS Independent
Requires-Python: >=3.6
License-File: LICENSE
